pep723/__init__.py
pep723/__main__.py
pep723/parser.py
pep723/tool/__init__.py
pep723/tool/__main__.py
pep723/tool/cli.py
pep723/tool/runner.py
pep723/tool/venv.py
pep723-0.0.1.dist-info/LICENSE
pep723-0.0.1.dist-info/METADATA
pep723-0.0.1.dist-info/WHEEL
pep723-0.0.1.dist-info/top_level.txt
pep723-0.0.1.dist-info/RECORD
